behavior_cloning/__init__.py
behavior_cloning/model.py
behavior_cloning/train.py
behavior_cloning/train_stacked.py
behavior_cloning/cifar10/__init__.py
behavior_cloning/cifar10/main.py
behavior_cloning/cifar10/models/__init__.py
behavior_cloning/cifar10/models/densenet.py
behavior_cloning/cifar10/models/dla.py
behavior_cloning/cifar10/models/dla_simple.py
behavior_cloning/cifar10/models/dpn.py
behavior_cloning/cifar10/models/efficientnet.py
behavior_cloning/cifar10/models/googlenet.py
behavior_cloning/cifar10/models/lenet.py
behavior_cloning/cifar10/models/mlp.py
behavior_cloning/cifar10/models/mobilenet.py
behavior_cloning/cifar10/models/mobilenetv2.py
behavior_cloning/cifar10/models/pnasnet.py
behavior_cloning/cifar10/models/preact_resnet.py
behavior_cloning/cifar10/models/regnet.py
behavior_cloning/cifar10/models/resnet.py
behavior_cloning/cifar10/models/resnext.py
behavior_cloning/cifar10/models/senet.py
behavior_cloning/cifar10/models/shufflenet.py
behavior_cloning/cifar10/models/shufflenetv2.py
behavior_cloning/cifar10/models/vgg.py
behavior_cloning/cifar10/models/wideresnet.py
behavior_cloning/go1_model/__init__.py
behavior_cloning/go1_model/actor.py
behavior_cloning/go1_model/ball_actor.py
behavior_cloning/go1_model/ball_actor_prop.py
behavior_cloning/go1_model/simple_vision_head.py
behavior_cloning/go1_model/transformers/__init__.py
behavior_cloning/go1_model/transformers/mqv_transformer.py
behavior_cloning/go1_model/transformers/parallem_transformer.py
behavior_cloning/go1_model/transformers/transformer_policy.py
lucidsim/__init__.py
lucidsim/parkour_vuer.py
lucidsim/tasks/__init__.py
lucidsim/tasks/chase.py
lucidsim/tasks/extensions.py
lucidsim/tasks/flat.py
lucidsim/tasks/gaps.py
lucidsim/tasks/hurdle.py
lucidsim/tasks/parkour.py
lucidsim/tasks/real.py
lucidsim/tasks/stairs.py
lucidsim/tasks/base/__init__.py
lucidsim/tasks/base/ball.py
lucidsim/tasks/base/go1_base.py
lucidsim/tasks/base/two_balls.py
lucidsim/traj_samplers/__init__.py
lucidsim-0.0.1rc1.dist-info/LICENSE
lucidsim-0.0.1rc1.dist-info/METADATA
lucidsim-0.0.1rc1.dist-info/WHEEL
lucidsim-0.0.1rc1.dist-info/top_level.txt
lucidsim-0.0.1rc1.dist-info/RECORD
