Metadata-Version: 2.1
Name: lucidsim
Version: 0.0.1rc1
Summary: LucidSim and Benchmark Suite
Home-page: https://github.com/embodied-intelligence/lucidsim
Author: Ge Yang<ge.ike.yang@gmail.com>
Author-email: ge.ike.yang@gmail.com
License-File: LICENSE
Requires-Dist: params-proto
Requires-Dist: numpy
Requires-Dist: pillow
